daxpy/__init__.py
daxpy-0.2.dist-info/LICENSE
daxpy-0.2.dist-info/METADATA
daxpy-0.2.dist-info/WHEEL
daxpy-0.2.dist-info/top_level.txt
daxpy-0.2.dist-info/RECORD
